.coveragerc
.gitignore
.gitlab-ci.yml
.update_coverage
LICENSE
MANIFEST.in
Makefile
README.rst
policyd-rate-limit
pytest.ini
requirements-dev.txt
setup.cfg
setup.py
tox.ini
.github/workflows/github-actions.yml
docs/policyd-rate-limit.8.rst
docs/policyd-rate-limit.yaml.5.rst
init/policyd-rate-limit
init/policyd-rate-limit-clean.service
init/policyd-rate-limit-clean.timer
init/policyd-rate-limit.service
policyd_rate_limit/__init__.py
policyd_rate_limit/config.py
policyd_rate_limit/const.py
policyd_rate_limit/policyd-rate-limit.conf
policyd_rate_limit/policyd-rate-limit.yaml
policyd_rate_limit/policyd.py
policyd_rate_limit/utils.py
policyd_rate_limit.egg-info/PKG-INFO
policyd_rate_limit.egg-info/SOURCES.txt
policyd_rate_limit.egg-info/dependency_links.txt
policyd_rate_limit.egg-info/not-zip-safe
policyd_rate_limit.egg-info/requires.txt
policyd_rate_limit.egg-info/top_level.txt
policyd_rate_limit/tests/__init__.py
policyd_rate_limit/tests/test_daemon.py
policyd_rate_limit/tests/utils.py