Metadata-Version: 1.1
Name: policyd-rate-limit
Version: 1.2.0
Summary: Postfix rate limit policy server implemented in Python3.
Home-page: https://github.com/nitmir/policyd-rate-limit
Author: Valentin Samir
Author-email: valentin.samir@crans.org
License: GPLv3
Download-URL: https://github.com/nitmir/policyd-rate-limit/releases/latest
Keywords: Postfix,rate,limit,email
Platform: UNKNOWN
Classifier: Environment :: No Input/Output (Daemon)
Classifier: Intended Audience :: Developers
Classifier: License :: OSI Approved :: GNU General Public License v3 (GPLv3)
Classifier: Operating System :: POSIX
Classifier: Programming Language :: Python
Classifier: Programming Language :: Python :: 3
Classifier: Topic :: Communications :: Email :: Mail Transport Agents
Classifier: Topic :: Communications :: Email :: Filters
